CHANGES.txt
LICENSE.txt
MANIFEST.in
README.md
setup.py
bin/tosu
todo_summary/__init__.py
todo_summary/app.py
todo_summary/notifier.py
todo_summary/sound.py
todo_summary/todo.py
todo_summary/widgets.py
todo_summary.egg-info/PKG-INFO
todo_summary.egg-info/SOURCES.txt
todo_summary.egg-info/dependency_links.txt
todo_summary.egg-info/requires.txt
todo_summary.egg-info/top_level.txt
todo_summary/sound_effects/horn.wav
todo_summary/sound_effects/paper.wav
todo_summary/sound_effects/scifi_start.wav
todo_summary/sound_effects/thermo.wav
todo_summary/test/__init__.py
todo_summary/test/test_summary.py
todo_summary/test/test_todo.py