Metadata-Version: 1.0
Name: todo-summary
Version: 0.1.3
Summary: todo-summary simply combines todo and summary.
Home-page: http://pypi.python.org/pypi/todo-summary/
Author: Ruoran Wang
Author-email: dashuiwa@gmail.com
License:     todo-summary combines todo and summary.
